./.gitignore
./LICENSE
./PKG-INFO
./README.md
./config.json
./nbtest_gen.py
./pyproject.toml
./assert_gen/assertionGenerator.py
./assert_gen/functionTransformer.py
./assert_gen/notebookRunner.py
./nbtest_demo/environment.yml
./nbtest_demo/house-prices-advanced-regression-techniques.ipynb
./nbtest_demo/kernel-metadata.json
./nbtest_demo/input/data_description.txt
./nbtest_demo/input/sample_submission.csv
./nbtest_demo/input/test.csv
./nbtest_demo/input/train.csv
./properties/functionTransformer.py
./properties/propertyFinder.py
./utils/pytest_run.py
./utils/read_pickle.py
./utils/utils.py
nbtest_gen-0.1.8.dist-info/METADATA
nbtest_gen-0.1.8.dist-info/WHEEL
nbtest_gen-0.1.8.dist-info/entry_points.txt
nbtest_gen-0.1.8.dist-info/licenses/LICENSE
nbtest_gen-0.1.8.dist-info/RECORD
