Metadata-Version: 2.4
Name: nbtest-gen
Version: 0.1.8
Summary: Comprehensive Framework for generating high-quality assertions (tests) for Jupyter Notebooks
License-File: LICENSE
Classifier: Framework :: Pytest
Requires-Dist: matplotlib
Requires-Dist: nbformat
Requires-Dist: nbtest-plugin
Requires-Dist: numpy
Requires-Dist: pandas
